pazer_dataform_python/__init__.py
test/__init__.py
pazer_dataform_python-0.4.1.dist-info/LICENSE
pazer_dataform_python-0.4.1.dist-info/METADATA
pazer_dataform_python-0.4.1.dist-info/WHEEL
pazer_dataform_python-0.4.1.dist-info/top_level.txt
pazer_dataform_python-0.4.1.dist-info/RECORD
