Metadata-Version: 2.1
Name: pazer_dataform_python
Version: 0.4.1
Summary: Pazer DataForm - Python
Author: David Kim
Author-email: David Kim <woody@woody.co.kr>
Project-URL: Homepage, https://github.com/pazer-app/pazer_dataform_python
Project-URL: Bug Tracker, https://github.com/pazer-app/pazer_dataform_python/issues
Keywords: pazer,dataform
Classifier: Programming Language :: Python :: 3
Classifier: License :: OSI Approved :: MIT License
Classifier: Operating System :: OS Independent
Requires-Python: >=3.7
License-File: LICENSE
Requires-Dist: fastapi>=0.115.6
Requires-Dist: pydantic>=2.10.4
